{"name":"Test Report","logo":null,"date":1746666008677,"dateH":"5/8/2025, 1:00:08 AM","duration":8941,"durationH":"8.9s","cwd":"/home/runner/work/playwright-test/playwright-test","outputFile":"/home/runner/work/playwright-test/playwright-test/test-reports/monocart/index.html","outputDir":"/home/runner/work/playwright-test/playwright-test/test-reports/monocart","metadata":{"ci":{"commitHref":"https://github.com/miranda-wqa/playwright-test/commit/a3cf3b6b40ad75a1a60dd46d819ddf1201b10b25","commitHash":"a3cf3b6b40ad75a1a60dd46d819ddf1201b10b25","buildHref":"https://github.com/miranda-wqa/playwright-test/actions/runs/14896283607"},"gitCommit":{"shortHash":"a3cf3b6","hash":"a3cf3b6b40ad75a1a60dd46d819ddf1201b10b25","subject":"change","body":"change\n","author":{"name":"miranda-wqa","email":"miranda-wqa@gmail.com","time":1746665403000},"committer":{"name":"miranda-wqa","email":"miranda-wqa@gmail.com","time":1746665403000},"branch":"main"},"actualWorkers":1},"system":{"cpu":{"color":"#117DBB","count":4,"model":"AMD EPYC 7763 64-Core Processor","speed":0},"mem":{"color":"#8B12AE","total":16766410752},"arch":"x64","platform":"linux","release":"6.11.0-1013-azure","type":"Linux","version":"#13~24.04.1-Ubuntu SMP Fri Mar 28 23:43:34 UTC 2025","uptime":543.32,"hostname":"fv-az1912-631","pid":4903,"node":"22.15.0","v8":"12.4.254.21-node.24","timestampStart":1746666008677,"ticks":[{"cpu":{"percent":32.42},"mem":{"free":15401791488},"timestamp":1746666010680},{"cpu":{"percent":80.88},"mem":{"free":15235178496},"timestamp":1746666012681},{"cpu":{"percent":35.2},"mem":{"free":15301136384},"timestamp":1746666014682},{"cpu":{"percent":49.23},"mem":{"free":15377121280},"timestamp":1746666016684},{"cpu":{"percent":2.26},"mem":{"free":15394201600},"timestamp":1746666017615}],"workers":1,"jobs":[{"caseId":"f14f610617654fe66339","parallelIndex":0,"workerIndex":0,"timestamp":1746666009438,"duration":2459},{"caseId":"b80953c721698d32a40e","parallelIndex":0,"workerIndex":0,"timestamp":1746666011898,"duration":406},{"caseId":"a06e240975c76a477617","parallelIndex":0,"workerIndex":0,"timestamp":1746666012304,"duration":361},{"caseId":"dd5c8503f541b3debbb1","parallelIndex":0,"workerIndex":0,"timestamp":1746666012665,"duration":351},{"caseId":"5f3d34a7e5ba6c2d5a12","parallelIndex":-1,"workerIndex":-1,"timestamp":1746666013016,"duration":0},{"caseId":"fd866c6ab98efdc3a526","parallelIndex":0,"workerIndex":0,"timestamp":1746666013017,"duration":799},{"caseId":"fd866c6ab98efdc3a526","parallelIndex":0,"workerIndex":1,"timestamp":1746666014448,"duration":721},{"caseId":"fd866c6ab98efdc3a526","parallelIndex":0,"workerIndex":2,"timestamp":1746666015796,"duration":753}],"cwd":"/home/runner/work/playwright-test/playwright-test","configFile":"playwright.config.ts","playwright":"1.51.1","monocart":"2.9.17","testDir":"tests","outputFile":"test-reports/monocart/index.html","outputDir":"test-reports/monocart","timestampEnd":1746666017618},"artifacts":[],"trends":[],"columns":[{"id":"caseType","name":"","width":36,"sortable":false,"align":"center","formatter":"iconCaseType","detailed":false},{"id":"title","name":"Title","searchable":true,"width":350,"maxWidth":1230,"detailed":false},{"id":"type","name":"Type","width":50,"sortable":false,"align":"center","formatter":"iconType","detailed":false},{"id":"duration","name":"Duration","align":"right","sortAsc":false,"formatter":"duration","detailed":false},{"id":"errors","name":"Errors","width":60,"align":"center","comparer":"errors","formatter":"errors","detailed":false},{"id":"logs","name":"Logs","width":60,"align":"center","comparer":"logs","formatter":"logs","detailed":false},{"id":"annotations","name":"Annotations","width":100,"markdown":true,"searchable":true,"comparer":"annotations","formatter":"annotations","detailed":false},{"id":"attachments","name":"Attachments","width":100,"align":"center","formatter":"attachments","detailed":false},{"id":"status","name":"Status","align":"center","detailed":false},{"id":"expectedStatus","name":"Expected","align":"center","detailed":false},{"id":"outcome","name":"Outcome","align":"center","width":85,"detailed":false},{"id":"retry","name":"Retry","align":"center","width":50,"detailed":false},{"id":"location","name":"Location","classMap":"mcr-location","width":200,"maxWidth":1981,"detailed":false}],"rows":[{"id":"252c5186032776190fb4","title":"chromium","type":"suite","suiteType":"project","caseNum":6,"subs":[{"id":"d6122e9e2b5322fc77fd","title":"playwright/test-1.spec.ts","type":"suite","suiteType":"file","caseNum":6,"subs":[{"id":"f14f610617654fe66339","title":"File 1: Test 1","type":"case","caseType":"passed","ok":true,"outcome":"expected","expectedStatus":"passed","location":"tests/playwright/test-1.spec.ts:3:5","logs":["File 1: Test 1\nBefore Each Hook\n","PASSED\n","After Each Hook\n\n"],"timestamps":[1746666009438,1746666011897],"duration":2459,"tags":[],"timeout":30000,"retry":0,"status":"passed","stepNum":15,"stepFailed":0,"stepSubs":true,"subs":[{"id":"4uwkc86kjjnzk6x9i973","title":"Before Hooks","type":"step","stepType":"hook","duration":2312,"location":"","subs":[{"id":"qzqmmta1rv7mxx8b39zo","title":"fixture: browser","type":"step","stepType":"fixture","duration":1860,"location":"","subs":[{"id":"zy3wmqgq611c8xqgacvr","title":"browserType.launch","type":"step","stepType":"pw:api","duration":1857,"location":""}]},{"id":"2s78r3p1bwfyexf8b02j","title":"fixture: context","type":"step","stepType":"fixture","duration":21,"location":"","subs":[{"id":"a49su6kkgxlr4k8kieyz","title":"browser.newContext","type":"step","stepType":"pw:api","duration":8,"location":""}]},{"id":"gljykhvd7ql6giw9wiei","title":"fixture: page","type":"step","stepType":"fixture","duration":48,"location":"","subs":[{"id":"uncfn0dmoa2q103cpfmv","title":"browserContext.newPage","type":"step","stepType":"pw:api","duration":46,"location":""}]},{"id":"mfwkghtle55q07eqer0e","title":"fixture: forEachTest","type":"step","stepType":"fixture","duration":371,"location":"tests/hook-2.ts:18:26","subs":[{"id":"0dzvqns8o0st3tdtaev8","title":"page.goto(https://playwright.dev/)","type":"step","stepType":"pw:api","duration":368,"location":"tests/hook-2.ts:22:16"}]}]},{"id":"0di3lqr156lkf4lczdby","title":"expect.toHaveTitle","type":"step","stepType":"expect","duration":90,"location":"tests/playwright/test-1.spec.ts:4:22"},{"id":"uta7k9ju8brzwymw1c22","title":"After Hooks","type":"step","stepType":"hook","duration":51,"location":"","subs":[{"id":"k4rcyl2c8farkvdtvwv6","title":"fixture: forEachTest","type":"step","stepType":"fixture","duration":17,"location":"tests/hook-2.ts:18:26","subs":[{"id":"xstrnnk5g9ee6qrkizho","title":"page.close","type":"step","stepType":"pw:api","duration":15,"location":"tests/hook-2.ts:29:16"}]},{"id":"k7zw79w8oy8pwikf0rsw","title":"fixture: page","type":"step","stepType":"fixture","duration":0,"location":""},{"id":"vd0f1q5yia14wgagj4m3","title":"fixture: context","type":"step","stepType":"fixture","duration":0,"location":""}]}]},{"id":"b80953c721698d32a40e","title":"File 1: Test 2","type":"case","caseType":"passed","ok":true,"outcome":"expected","expectedStatus":"passed","location":"tests/playwright/test-1.spec.ts:8:5","logs":["File 1: Test 2\nBefore Each Hook\n","PASSED\n","After Each Hook\n\n"],"timestamps":[1746666011898,1746666012304],"duration":406,"tags":[],"timeout":30000,"retry":0,"status":"passed","stepNum":13,"stepFailed":0,"stepSubs":true,"subs":[{"id":"i1fsnp09klbu03hkjmfm","title":"Before Hooks","type":"step","stepType":"hook","duration":278,"location":"","subs":[{"id":"6wvu7t3porj9p4jo59fd","title":"fixture: context","type":"step","stepType":"fixture","duration":6,"location":"","subs":[{"id":"s4ah4l01nfllxo0ot92i","title":"browser.newContext","type":"step","stepType":"pw:api","duration":3,"location":""}]},{"id":"ybit30xdb0z0w1vevmld","title":"fixture: page","type":"step","stepType":"fixture","duration":26,"location":"","subs":[{"id":"v67e1ffdja4kfmwzfnky","title":"browserContext.newPage","type":"step","stepType":"pw:api","duration":25,"location":""}]},{"id":"yr9p57yvgkxwkne5ta72","title":"fixture: forEachTest","type":"step","stepType":"fixture","duration":243,"location":"tests/hook-2.ts:18:26","subs":[{"id":"jdz8h8uw5knrmulcui4y","title":"page.goto(https://playwright.dev/)","type":"step","stepType":"pw:api","duration":242,"location":"tests/hook-2.ts:22:16"}]}]},{"id":"3puasyicozi2d3kh6srm","title":"expect.toHaveTitle","type":"step","stepType":"expect","duration":70,"location":"tests/playwright/test-1.spec.ts:9:22"},{"id":"znw9rjx2xjzyhbxmmwgg","title":"After Hooks","type":"step","stepType":"hook","duration":55,"location":"","subs":[{"id":"be0xo0ipvace7jmlqrze","title":"fixture: forEachTest","type":"step","stepType":"fixture","duration":20,"location":"tests/hook-2.ts:18:26","subs":[{"id":"jyo60e8bhymterbgpe4z","title":"page.close","type":"step","stepType":"pw:api","duration":19,"location":"tests/hook-2.ts:29:16"}]},{"id":"vd204qtnppos7h9gsyx1","title":"fixture: page","type":"step","stepType":"fixture","duration":0,"location":""},{"id":"4epr7dskumxxbvgu2hnz","title":"fixture: context","type":"step","stepType":"fixture","duration":0,"location":""}]}]},{"id":"a06e240975c76a477617","title":"File 1: Test 3","type":"case","caseType":"passed","ok":true,"outcome":"expected","expectedStatus":"passed","location":"tests/playwright/test-1.spec.ts:13:5","logs":["File 1: Test 3\nBefore Each Hook\n","PASSED\n","After Each Hook\n\n"],"timestamps":[1746666012304,1746666012665],"duration":361,"tags":[],"timeout":30000,"retry":0,"status":"passed","stepNum":13,"stepFailed":0,"stepSubs":true,"subs":[{"id":"0krz91z9oeei6wvecsos","title":"Before Hooks","type":"step","stepType":"hook","duration":246,"location":"","subs":[{"id":"d15kbmlk2h9yzqyuplne","title":"fixture: context","type":"step","stepType":"fixture","duration":5,"location":"","subs":[{"id":"3y7b6p8bbq6nj6ks7gyx","title":"browser.newContext","type":"step","stepType":"pw:api","duration":3,"location":""}]},{"id":"t6x0ancphazk7pvsu1dh","title":"fixture: page","type":"step","stepType":"fixture","duration":29,"location":"","subs":[{"id":"wwje1s0a7tvizy73yhyt","title":"browserContext.newPage","type":"step","stepType":"pw:api","duration":27,"location":""}]},{"id":"ktu3z0dza4wc2jge419v","title":"fixture: forEachTest","type":"step","stepType":"fixture","duration":211,"location":"tests/hook-2.ts:18:26","subs":[{"id":"opfmxfv88jku75fbn0wt","title":"page.goto(https://playwright.dev/)","type":"step","stepType":"pw:api","duration":209,"location":"tests/hook-2.ts:22:16"}]}]},{"id":"djsql62hsu5s2uuisgw0","title":"expect.toHaveTitle","type":"step","stepType":"expect","duration":73,"location":"tests/playwright/test-1.spec.ts:14:22"},{"id":"3jcixsvqn6naekqb6wzn","title":"After Hooks","type":"step","stepType":"hook","duration":39,"location":"","subs":[{"id":"mpthho1qtp5lz9z013zf","title":"fixture: forEachTest","type":"step","stepType":"fixture","duration":10,"location":"tests/hook-2.ts:18:26","subs":[{"id":"jdzbzgvzc7x05ocgwace","title":"page.close","type":"step","stepType":"pw:api","duration":9,"location":"tests/hook-2.ts:29:16"}]},{"id":"mw44atbv4h450ffi5wnl","title":"fixture: page","type":"step","stepType":"fixture","duration":0,"location":""},{"id":"yh1qpwpsqfimxj9p5nnu","title":"fixture: context","type":"step","stepType":"fixture","duration":0,"location":""}]}]},{"id":"dd5c8503f541b3debbb1","title":"File 1: Test 4","type":"case","caseType":"passed","ok":true,"outcome":"expected","expectedStatus":"passed","location":"tests/playwright/test-1.spec.ts:18:5","logs":["File 1: Test 4\nBefore Each Hook\n","PASSED\n","After Each Hook\n\n"],"timestamps":[1746666012665,1746666013016],"duration":351,"tags":[],"timeout":30000,"retry":0,"status":"passed","stepNum":13,"stepFailed":0,"stepSubs":true,"subs":[{"id":"t6sfp7d99jm8pujqb2jw","title":"Before Hooks","type":"step","stepType":"hook","duration":260,"location":"","subs":[{"id":"1m5lmahrokmmmlx9iayc","title":"fixture: context","type":"step","stepType":"fixture","duration":5,"location":"","subs":[{"id":"23jl0lgy5bpiidqmziy3","title":"browser.newContext","type":"step","stepType":"pw:api","duration":2,"location":""}]},{"id":"xy6bs0y7zsfd3eck64ez","title":"fixture: page","type":"step","stepType":"fixture","duration":26,"location":"","subs":[{"id":"y4btursq6eydw9n0nf2v","title":"browserContext.newPage","type":"step","stepType":"pw:api","duration":25,"location":""}]},{"id":"tocf3nfvqtocx9q2oraq","title":"fixture: forEachTest","type":"step","stepType":"fixture","duration":228,"location":"tests/hook-2.ts:18:26","subs":[{"id":"pd8wnj4olc3u5w9kfmtu","title":"page.goto(https://playwright.dev/)","type":"step","stepType":"pw:api","duration":226,"location":"tests/hook-2.ts:22:16"}]}]},{"id":"fhv4rteoojjqu8jdx5nm","title":"expect.toHaveTitle","type":"step","stepType":"expect","duration":41,"location":"tests/playwright/test-1.spec.ts:19:22"},{"id":"8z5u1pxklkr53zv4884o","title":"After Hooks","type":"step","stepType":"hook","duration":47,"location":"","subs":[{"id":"813znxxiva3nly1nphd5","title":"fixture: forEachTest","type":"step","stepType":"fixture","duration":18,"location":"tests/hook-2.ts:18:26","subs":[{"id":"8qfqh1m8jo2t7kqze262","title":"page.close","type":"step","stepType":"pw:api","duration":16,"location":"tests/hook-2.ts:29:16"}]},{"id":"w8vdayagr3ondnknc641","title":"fixture: page","type":"step","stepType":"fixture","duration":1,"location":""},{"id":"s1p3z0nl69yw9wf4l89y","title":"fixture: context","type":"step","stepType":"fixture","duration":0,"location":""}]}]},{"id":"5f3d34a7e5ba6c2d5a12","title":"File 1: Test 5","type":"case","caseType":"skipped","ok":true,"outcome":"skipped","expectedStatus":"skipped","location":"tests/playwright/test-1.spec.ts:23:6","timestamps":[1746666013016,1746666013016],"duration":0,"annotations":[{"type":"skip"}],"tags":[],"timeout":30000,"retry":0,"status":"skipped","stepNum":0,"stepFailed":0,"stepSubs":false},{"id":"fd866c6ab98efdc3a526","title":"File 1: Test 6","type":"case","caseType":"failed","ok":false,"outcome":"unexpected","expectedStatus":"passed","location":"tests/playwright/test-1.spec.ts:28:5","logs":["File 1: Test 6\nBefore Each Hook\n","After Each Hook\n\n","\nRetry #1\n","File 1: Test 6\nBefore Each Hook\n","After Each Hook\n\n","\nRetry #2\n","File 1: Test 6\nBefore Each Hook\n","After Each Hook\n\n"],"timestamps":[1746666013017,1746666013816,1746666014448,1746666015169,1746666015796,1746666016549],"duration":3532,"tags":[],"timeout":30000,"errors":["Error: This test failed on purpose!\n\n\u001b[0m \u001b[90m 27 |\u001b[39m\n \u001b[90m 28 |\u001b[39m test(\u001b[32m'File 1: Test 6'\u001b[39m\u001b[33m,\u001b[39m \u001b[36masync\u001b[39m ({ }) \u001b[33m=>\u001b[39m {\n\u001b[31m\u001b[1m>\u001b[22m\u001b[39m\u001b[90m 29 |\u001b[39m   \u001b[36mthrow\u001b[39m \u001b[36mnew\u001b[39m \u001b[33mError\u001b[39m(\u001b[32m\"This test failed on purpose!\"\u001b[39m)\u001b[33m;\u001b[39m\n \u001b[90m    |\u001b[39m         \u001b[31m\u001b[1m^\u001b[22m\u001b[39m\u001b[0m\n\n    at /home/runner/work/playwright-test/playwright-test/tests/playwright/test-1.spec.ts:29:9","Error: This test failed on purpose!\n\n\u001b[0m \u001b[90m 27 |\u001b[39m\n \u001b[90m 28 |\u001b[39m test(\u001b[32m'File 1: Test 6'\u001b[39m\u001b[33m,\u001b[39m \u001b[36masync\u001b[39m ({ }) \u001b[33m=>\u001b[39m {\n\u001b[31m\u001b[1m>\u001b[22m\u001b[39m\u001b[90m 29 |\u001b[39m   \u001b[36mthrow\u001b[39m \u001b[36mnew\u001b[39m \u001b[33mError\u001b[39m(\u001b[32m\"This test failed on purpose!\"\u001b[39m)\u001b[33m;\u001b[39m\n \u001b[90m    |\u001b[39m         \u001b[31m\u001b[1m^\u001b[22m\u001b[39m\u001b[0m\n\n    at /home/runner/work/playwright-test/playwright-test/tests/playwright/test-1.spec.ts:29:9","Error: This test failed on purpose!\n\n\u001b[0m \u001b[90m 27 |\u001b[39m\n \u001b[90m 28 |\u001b[39m test(\u001b[32m'File 1: Test 6'\u001b[39m\u001b[33m,\u001b[39m \u001b[36masync\u001b[39m ({ }) \u001b[33m=>\u001b[39m {\n\u001b[31m\u001b[1m>\u001b[22m\u001b[39m\u001b[90m 29 |\u001b[39m   \u001b[36mthrow\u001b[39m \u001b[36mnew\u001b[39m \u001b[33mError\u001b[39m(\u001b[32m\"This test failed on purpose!\"\u001b[39m)\u001b[33m;\u001b[39m\n \u001b[90m    |\u001b[39m         \u001b[31m\u001b[1m^\u001b[22m\u001b[39m\u001b[0m\n\n    at /home/runner/work/playwright-test/playwright-test/tests/playwright/test-1.spec.ts:29:9"],"retry":2,"status":"failed","stepNum":52,"stepFailed":0,"stepSubs":true,"subs":[{"id":"nw4xupgcdq0ig2kkabaz","title":"Before Hooks","type":"step","stepType":"hook","duration":232,"location":"","subs":[{"id":"ovvpp7r1ukerkxu9rzws","title":"fixture: context","type":"step","stepType":"fixture","duration":8,"location":"","subs":[{"id":"xk6vnd92hz2lavcdfs4f","title":"browser.newContext","type":"step","stepType":"pw:api","duration":2,"location":""}]},{"id":"5q18urpawc8teact5udq","title":"fixture: page","type":"step","stepType":"fixture","duration":25,"location":"","subs":[{"id":"41phr01nci0iul20mzid","title":"browserContext.newPage","type":"step","stepType":"pw:api","duration":24,"location":""}]},{"id":"r4wntkrd2u8djlzkp8ja","title":"fixture: forEachTest","type":"step","stepType":"fixture","duration":197,"location":"tests/hook-2.ts:18:26","subs":[{"id":"qj8vvqcmhke7l8p3diss","title":"page.goto(https://playwright.dev/)","type":"step","stepType":"pw:api","duration":196,"location":"tests/hook-2.ts:22:16"}]}]},{"id":"ifkuf7xvm3lhl0f85lqv","title":"After Hooks","type":"step","stepType":"hook","duration":216,"location":"","subs":[{"id":"8jzwa23j195al8f4rvvo","title":"page.screenshot","type":"step","stepType":"pw:api","duration":131,"location":""},{"id":"67j8h88rcmd4in4knf1z","title":"fixture: forEachTest","type":"step","stepType":"fixture","duration":5,"location":"tests/hook-2.ts:18:26","subs":[{"id":"xvz8ic74irvqsn8exnzh","title":"page.close","type":"step","stepType":"pw:api","duration":4,"location":"tests/hook-2.ts:29:16"}]},{"id":"q63g5se4kj0vqvz16852","title":"fixture: page","type":"step","stepType":"fixture","duration":0,"location":""},{"id":"iyk3to1thh13txr67kkt","title":"fixture: context","type":"step","stepType":"fixture","duration":0,"location":""},{"id":"5sdq3dwvk36wqvq190i7","title":"video.saveAs","type":"step","stepType":"pw:api","duration":0,"location":""}]},{"id":"pabgouqa4g9rv0gzcs34","title":"Worker Cleanup","type":"step","stepType":"hook","duration":262,"location":"","subs":[{"id":"9yglljd47um6p21pgxls","title":"fixture: browser","type":"step","stepType":"fixture","duration":261,"location":""}]},{"id":"iobsmott1vfgktoicsye","title":"Retry #1","type":"step","stepType":"retry","status":"retry","retry":1},{"id":"sd7qiabe6lzlkt1gq1es","title":"Before Hooks","type":"step","stepType":"hook","duration":373,"location":"","subs":[{"id":"995wp267lscmlda4yuyi","title":"fixture: browser","type":"step","stepType":"fixture","duration":91,"location":"","subs":[{"id":"6fjlucb68y06omjgzss6","title":"browserType.launch","type":"step","stepType":"pw:api","duration":89,"location":""}]},{"id":"ljwqqd2f056mpdjttmo9","title":"fixture: context","type":"step","stepType":"fixture","duration":22,"location":"","subs":[{"id":"nuc04dhjnnu1uagijizw","title":"browser.newContext","type":"step","stepType":"pw:api","duration":9,"location":""}]},{"id":"lcghsbfri2habgxeva8y","title":"fixture: page","type":"step","stepType":"fixture","duration":37,"location":"","subs":[{"id":"xesm5qhfx44tt0uooghs","title":"browserContext.newPage","type":"step","stepType":"pw:api","duration":35,"location":""}]},{"id":"0nvrvhkesrems16j3rtb","title":"fixture: forEachTest","type":"step","stepType":"fixture","duration":215,"location":"tests/hook-2.ts:18:26","subs":[{"id":"f0345dpsxi3861tu4hfa","title":"page.goto(https://playwright.dev/)","type":"step","stepType":"pw:api","duration":214,"location":"tests/hook-2.ts:22:16"}]}]},{"id":"2xnu2j72ymc1daaxk1ia","title":"After Hooks","type":"step","stepType":"hook","duration":228,"location":"","subs":[{"id":"yzrzhdsfqytlfk2802lr","title":"page.screenshot","type":"step","stepType":"pw:api","duration":134,"location":""},{"id":"liuj1ww7ify3iw53mzbo","title":"fixture: forEachTest","type":"step","stepType":"fixture","duration":7,"location":"tests/hook-2.ts:18:26","subs":[{"id":"uo35c45kdgzemoc9lou4","title":"page.close","type":"step","stepType":"pw:api","duration":5,"location":"tests/hook-2.ts:29:16"}]},{"id":"gs0uwvqhkw1vo0xg30yn","title":"fixture: page","type":"step","stepType":"fixture","duration":0,"location":""},{"id":"ru38gfgonux9rrardjni","title":"fixture: context","type":"step","stepType":"fixture","duration":1,"location":""},{"id":"j417vmz17fqo5x62lgl0","title":"video.saveAs","type":"step","stepType":"pw:api","duration":0,"location":""}]},{"id":"17kd4hh2idfhevjniuj3","title":"Worker Cleanup","type":"step","stepType":"hook","duration":30,"location":"","subs":[{"id":"3pt8d47t98ewomp7ss6v","title":"fixture: browser","type":"step","stepType":"fixture","duration":30,"location":""}]},{"id":"kuygcgzuekjez3w8598k","title":"Retry #2","type":"step","stepType":"retry","status":"retry","retry":2},{"id":"y3mzpmnhiah738scklcg","title":"Before Hooks","type":"step","stepType":"hook","duration":386,"location":"","subs":[{"id":"ticpb7tmcsxyklrjwkfb","title":"fixture: browser","type":"step","stepType":"fixture","duration":103,"location":"","subs":[{"id":"2ex9ik80pwlme86pxyq2","title":"browserType.launch","type":"step","stepType":"pw:api","duration":100,"location":""}]},{"id":"z0q14d3anmgc3f4e5vk5","title":"fixture: context","type":"step","stepType":"fixture","duration":18,"location":"","subs":[{"id":"k3mpoir09dm0jjc93lut","title":"browser.newContext","type":"step","stepType":"pw:api","duration":6,"location":""}]},{"id":"kyjm2qce6hb4moyf3axq","title":"fixture: page","type":"step","stepType":"fixture","duration":36,"location":"","subs":[{"id":"myetx2cgi83mj2xmbhz4","title":"browserContext.newPage","type":"step","stepType":"pw:api","duration":34,"location":""}]},{"id":"9th3urgxsulqxgcx2sn1","title":"fixture: forEachTest","type":"step","stepType":"fixture","duration":218,"location":"tests/hook-2.ts:18:26","subs":[{"id":"z6cxez7lxsd8r39c9cad","title":"page.goto(https://playwright.dev/)","type":"step","stepType":"pw:api","duration":217,"location":"tests/hook-2.ts:22:16"}]}]},{"id":"ekllr02nzdl3nwovsjwc","title":"After Hooks","type":"step","stepType":"hook","duration":226,"location":"","subs":[{"id":"u4l41y1u3shjxlnkg577","title":"page.screenshot","type":"step","stepType":"pw:api","duration":135,"location":""},{"id":"ynqu6mirkkbfq54zhd5d","title":"fixture: forEachTest","type":"step","stepType":"fixture","duration":6,"location":"tests/hook-2.ts:18:26","subs":[{"id":"xvu1n7dfa15v4rfiya7r","title":"page.close","type":"step","stepType":"pw:api","duration":5,"location":"tests/hook-2.ts:29:16"}]},{"id":"mkexutvk0nq6dpf89lfc","title":"fixture: page","type":"step","stepType":"fixture","duration":0,"location":""},{"id":"kuj6m9htkth3wlwz9wik","title":"fixture: context","type":"step","stepType":"fixture","duration":0,"location":""},{"id":"tc3vtegxjf6f5v7s8664","title":"video.saveAs","type":"step","stepType":"pw:api","duration":1,"location":""}]},{"id":"mtypip3r7m6u6fwj4kuv","title":"Worker Cleanup","type":"step","stepType":"hook","duration":30,"location":"","subs":[{"id":"5ze4tjj1z98ltxwh8ysd","title":"fixture: browser","type":"step","stepType":"fixture","duration":30,"location":""}]}],"attachments":[{"name":"screenshot","path":"attachments/40a42250c8a65a4b5802cdcafd8682cff19c5034.png","contentType":"image/png","retry":0},{"name":"video","path":"attachments/0c0d8c3f96c7d5368c4d667e432e04158efe767a.webm","contentType":"video/webm","retry":0},{"name":"trace","path":"attachments/e3152678856889b71bb9ed55424b8a7560f5d0f5.zip","contentType":"application/zip","retry":0},{"name":"screenshot","path":"attachments/0adb5a8a33dd38693d7b7c0d7c68cdefad132a69.png","contentType":"image/png","retry":1},{"name":"video","path":"attachments/1dd17581407e48d8175e3c3ff37e003056c05701.webm","contentType":"video/webm","retry":1},{"name":"trace","path":"attachments/26cef173fce1b18e26c415b4259fac77e4df3d88.zip","contentType":"application/zip","retry":1},{"name":"screenshot","path":"attachments/829f1708d7b0558e7f66257ad4a46a9fcb5e0862.png","contentType":"image/png","retry":2},{"name":"video","path":"attachments/e28bcc101b461f327345ebe07f776efc21d2d5cd.webm","contentType":"video/webm","retry":2},{"name":"trace","path":"attachments/0fefb331b0703603c64b7119b4f4bdecb3bbf6e3.zip","contentType":"application/zip","retry":2}],"errorNum":3}],"location":"tests/playwright/test-1.spec.ts:0:0"}]}],"formatters":{},"suiteTypes":["project","file","describe","shard"],"caseTypes":["failed","flaky","skipped","passed"],"traceViewerUrl":"https://trace.playwright.dev/?trace={traceUrl}","mermaid":null,"groupOptions":null,"tags":{},"summary":{"tests":{"name":"Tests","value":6,"nav":true,"id":"tests"},"failed":{"name":"Failed","value":1,"color":"#d00","nav":true,"id":"failed","percent":"16.7%"},"flaky":{"name":"Flaky","value":0,"color":"orange","nav":true,"id":"flaky","percent":"0.0%"},"skipped":{"name":"Skipped","value":1,"color":"gray","nav":true,"id":"skipped","percent":"16.7%"},"passed":{"name":"Passed","value":4,"color":"green","nav":true,"id":"passed","percent":"66.7%"},"steps":{"name":"Steps","value":108,"id":"steps"},"suites":{"name":"Suites","value":1,"id":"suites"},"projects":{"name":"Projects","description":"Suite type is project","value":1,"id":"projects"},"files":{"name":"Files","description":"Suite type is file","value":1,"id":"files"},"describes":{"name":"Describes","description":"Suite type is describe","value":0,"id":"describes"},"shards":{"name":"Shards","description":"Suite type is shard (only in shading mode)","value":0,"id":"shards"},"errors":{"name":"Errors","icon":"error","value":3,"id":"errors"},"retries":{"name":"Retries","icon":"retry","value":2,"id":"retries"},"logs":{"name":"Logs","icon":"log","value":20,"id":"logs"},"attachments":{"name":"Attachments","icon":"attachment","value":9,"id":"attachments"},"artifacts":{"name":"Artifacts","value":0}},"pieChart":{"ns":"mcr-pie","width":360,"height":150,"margin":10,"svg":"<svg viewBox=\"0 0 360 150\" width=\"100%\" height=\"100%\" xmlns=\"http://www.w3.org/2000/svg\"><g class=\"mcr-pie-path-failed\"><path d=\"M75,75 L75,10 A65,65 0 0 1 131.4,42.6 z\" fill=\"#d00\" opacity=\"0.8\" /><animateTransform from=\"0,0\" to=\"0,0\" pos=\"5,-8.7\" attributeName=\"transform\" type=\"translate\" dur=\"0.2s\" fill=\"freeze\" repeatCount=\"1\" restart=\"always\" /></g><g class=\"mcr-pie-path-flaky\"><path d=\"\" fill=\"orange\" opacity=\"0.8\" /><animateTransform from=\"0,0\" to=\"0,0\" pos=\"8.7,-5\" attributeName=\"transform\" type=\"translate\" dur=\"0.2s\" fill=\"freeze\" repeatCount=\"1\" restart=\"always\" /></g><g class=\"mcr-pie-path-skipped\"><path d=\"M75,75 L131.4,42.6 A65,65 0 0 1 131.2,107.7 z\" fill=\"gray\" opacity=\"0.8\" /><animateTransform from=\"0,0\" to=\"0,0\" pos=\"10,0\" attributeName=\"transform\" type=\"translate\" dur=\"0.2s\" fill=\"freeze\" repeatCount=\"1\" restart=\"always\" /></g><g class=\"mcr-pie-path-passed\"><path d=\"M75,75 L131.2,107.7 A65,65 0 1 1 75.4,10 z\" fill=\"green\" opacity=\"0.8\" /><animateTransform from=\"0,0\" to=\"0,0\" pos=\"-8.7,5\" attributeName=\"transform\" type=\"translate\" dur=\"0.2s\" fill=\"freeze\" repeatCount=\"1\" restart=\"always\" /></g><g transform=\"translate(160 15)\"><g class=\"mcr-pie-legend-failed\" transform=\"translate(0 0)\"><circle cx=\"10\" cy=\"15\" r=\"10\" fill=\"#d00\" opacity=\"0.8\" /><text x=\"30\" y=\"15\" alignment-baseline=\"middle\">Failed</text><text x=\"115\" y=\"15\" alignment-baseline=\"middle\" text-anchor=\"middle\">1</text><text x=\"190\" y=\"15\" alignment-baseline=\"middle\" text-anchor=\"end\">16.7%</text></g><g class=\"mcr-pie-legend-flaky\" transform=\"translate(0 30)\"><circle cx=\"10\" cy=\"15\" r=\"10\" fill=\"orange\" opacity=\"0.8\" /><text x=\"30\" y=\"15\" alignment-baseline=\"middle\">Flaky</text><text x=\"115\" y=\"15\" alignment-baseline=\"middle\" text-anchor=\"middle\">0</text><text x=\"190\" y=\"15\" alignment-baseline=\"middle\" text-anchor=\"end\">0.0%</text></g><g class=\"mcr-pie-legend-skipped\" transform=\"translate(0 60)\"><circle cx=\"10\" cy=\"15\" r=\"10\" fill=\"gray\" opacity=\"0.8\" /><text x=\"30\" y=\"15\" alignment-baseline=\"middle\">Skipped</text><text x=\"115\" y=\"15\" alignment-baseline=\"middle\" text-anchor=\"middle\">1</text><text x=\"190\" y=\"15\" alignment-baseline=\"middle\" text-anchor=\"end\">16.7%</text></g><g class=\"mcr-pie-legend-passed\" transform=\"translate(0 90)\"><circle cx=\"10\" cy=\"15\" r=\"10\" fill=\"green\" opacity=\"0.8\" /><text x=\"30\" y=\"15\" alignment-baseline=\"middle\">Passed</text><text x=\"115\" y=\"15\" alignment-baseline=\"middle\" text-anchor=\"middle\">4</text><text x=\"190\" y=\"15\" alignment-baseline=\"middle\" text-anchor=\"end\">66.7%</text></g></g></svg>"},"htmlPath":"test-reports/monocart/index.html"}
